{
  "id": "TPCDS_Test_Experiment_DS_POO_NOBOO_bao_v_256_2_v3",
  "description": "Just a TPCDS Test Experiment",
  "gym_version": 1,
  "timesteps": 20000,
  "random_seed": 62,
  "parallel_environments": 1,
  "pickle_cost_estimation_caches": false,
  "action_manager": "MultiColumnIndexActionManager",
  "observation_manager": "SingleColumnIndexPlanEmbeddingObservationManagerWithCost",
  "reward_calculator": "RelativeDifferenceRelativeToStorageReward",
  "max_steps_per_episode": 200,
  "validation_frequency": 1000,
  "filter_utilized_columns": false,
  "max_index_width": 3,
  "result_path": "experiment_results",
  "reenable_indexes": false,
  "workload_embedder": {
    "type": "PlanEmbedderLSIBOW",
    "representation_size": 50
  },
  "rl_algorithm": {
    "algorithm": "PPO2",
    "stable_baselines_version": 2,
    "gamma": 0.5,
    "policy": "MlpPolicy",
    "model_architecture": {
      "net_arch": [
        {
          "vf": [256,256],
          "pi": [256,256]
        }
      ]
    },
    "args": {
      "n_steps": 64
    }
  },
  "workload": {
    "benchmark": "TPCDS",
    "scale_factor": 1,
    "size": 40,
    "varying_frequencies": true,
    "training_instances": 2000,
    "validation_testing": {
      "number_of_workloads": 10,
      "unknown_query_probabilities": [0.0]
    },
    "similar_workloads": false,
    "excluded_query_classes": [4, 6, 9, 10, 11, 32, 35, 41, 95],
    "unknown_queries": 0
  },
  "comparison_algorithms": ["db2advis"],
  "budgets": {
    "training": true,
    "validation_and_testing": [500, 1000, 1500, 2500, 3500, 5000, 6500, 8000, 10000, 12500]
  },
  "column_filters": {
    "TableNumRowsFilter": 10000
  },
  "materialized_views": {
    "enabled": true,
    "max_count": 8,
    "max_index_width": 3,
    "similarity_threshold": 0.6,
    "representation_size": 50,
    "value_encoding_dim": 10,
    "hidden_dims": [128, 64],
    "output_dim": 32,
    "templates": [
      {
        "name": "mv_store_sales_summary",
        "sql": "SELECT ss_store_sk, ss_item_sk, SUM(ss_quantity) as total_quantity, SUM(ss_sales_price) as total_sales FROM store_sales GROUP BY ss_store_sk, ss_item_sk"
      },
      {
        "name": "mv_customer_demographics",
        "sql": "SELECT cd_demo_sk, cd_gender, cd_marital_status, cd_education_status, COUNT(*) as count FROM customer_demographics GROUP BY cd_demo_sk, cd_gender, cd_marital_status, cd_education_status"
      },
      {
        "name": "mv_date_dimension",
        "sql": "SELECT d_date_sk, d_year, d_moy, d_dom, d_weekday FROM date_dim WHERE d_year >= 1998 AND d_year <= 2002"
      },
      {
        "name": "mv_item_categories",
        "sql": "SELECT i_item_sk, i_category, i_class, i_brand, COUNT(*) as count FROM item GROUP BY i_item_sk, i_category, i_class, i_brand"
      }
    ],
    "rewrite_mappings": {
      "SELECT ss_store_sk, SUM(ss_quantity) FROM store_sales GROUP BY ss_store_sk": "SELECT ss_store_sk, total_quantity FROM mv_store_sales_summary GROUP BY ss_store_sk"
    }
  }
}
